django_plugin_extensions/__init__.py
django_plugin_extensions/py.typed
django_plugin_extensions-0.1.2.dist-info/WHEEL
django_plugin_extensions-0.1.2.dist-info/entry_points.txt
django_plugin_extensions-0.1.2.dist-info/METADATA
django_plugin_extensions-0.1.2.dist-info/RECORD
