Metadata-Version: 2.3
Name: django-plugin-extensions
Version: 0.1.2
Summary: Django plugin wrapping django-extensions
Author: Joel Sleppy
Author-email: Joel Sleppy <joel@sleppytech.com>
License: Apache-2.0
Classifier: License :: OSI Approved :: Apache Software License
Requires-Dist: django
Requires-Dist: djp>=0.3.1
Requires-Dist: django-extensions==4.*
